rag_bencher/__init__.py
rag_bencher/bench_cli.py
rag_bencher/bench_many_cli.py
rag_bencher/cli.py
rag_bencher/config.py
rag_bencher/py.typed
rag_bencher/eval/dataset_loader.py
rag_bencher/eval/metrics.py
rag_bencher/eval/report.py
rag_bencher/eval/datasets/__init__.py
rag_bencher/pipelines/base.py
rag_bencher/pipelines/hyde.py
rag_bencher/pipelines/multi_query.py
rag_bencher/pipelines/naive_rag.py
rag_bencher/pipelines/rerank.py
rag_bencher/pipelines/selector.py
rag_bencher/pipelines/utils.py
rag_bencher/providers/base.py
rag_bencher/providers/aws/__init__.py
rag_bencher/providers/aws/auth.py
rag_bencher/providers/aws/chat.py
rag_bencher/providers/aws/embeddings.py
rag_bencher/providers/azure/__init__.py
rag_bencher/providers/azure/auth.py
rag_bencher/providers/azure/chat.py
rag_bencher/providers/azure/embeddings.py
rag_bencher/providers/gcp/__init__.py
rag_bencher/providers/gcp/auth.py
rag_bencher/providers/gcp/chat.py
rag_bencher/providers/gcp/embeddings.py
rag_bencher/utils/cache.py
rag_bencher/utils/factories.py
rag_bencher/utils/hardware.py
rag_bencher/utils/io.py
rag_bencher/utils/logging.py
rag_bencher/utils/repro.py
rag_bencher/utils/resources.py
rag_bencher/utils/torch_utils.py
rag_bencher/utils/callbacks/__init__.py
rag_bencher/utils/callbacks/usage.py
rag_bencher/vector/azure_ai_search.py
rag_bencher/vector/base.py
rag_bencher/vector/local.py
rag_bencher/vector/matching_engine.py
rag_bencher/vector/opensearch.py
rag_bencher-0.0.4.dist-info/licenses/LICENSE
rag_bencher-0.0.4.dist-info/METADATA
rag_bencher-0.0.4.dist-info/WHEEL
rag_bencher-0.0.4.dist-info/entry_points.txt
rag_bencher-0.0.4.dist-info/top_level.txt
rag_bencher-0.0.4.dist-info/RECORD
