Metadata-Version: 2.4
Name: rag-bencher
Version: 0.0.4
Summary: Reproducible RAG baselines and evaluations with LangChain
Author: Mikael Twengström
License-Expression: MIT
Classifier: Development Status :: 3 - Alpha
Classifier: Intended Audience :: Developers
Classifier: Programming Language :: Python :: 3 :: Only
Classifier: Programming Language :: Python :: 3.12
Classifier: Programming Language :: Python :: 3.13
Classifier: Programming Language :: Python :: 3.14
Classifier: Topic :: Scientific/Engineering :: Artificial Intelligence
Requires-Python: <3.15,>=3.12
License-File: LICENSE
Requires-Dist: langchain>=0.2.0
Requires-Dist: langchain-community>=0.2.0
Requires-Dist: langchain-openai>=0.1.0
Requires-Dist: langchain-huggingface>=0.1.0
Requires-Dist: sentence-transformers>=2.2.2
Requires-Dist: faiss-cpu>=1.7.4
Requires-Dist: pydantic>=2.7.0
Requires-Dist: pyyaml>=6.0.1
Requires-Dist: rich>=13.7.0
Requires-Dist: numpy>=1.26.0
Provides-Extra: dev
Requires-Dist: tox>=4.32.0; extra == "dev"
Requires-Dist: pytest>=7.4.0; extra == "dev"
Requires-Dist: pytest-cov>=4.1.0; extra == "dev"
Requires-Dist: black>=24.4.0; extra == "dev"
Requires-Dist: isort>=5.13.0; extra == "dev"
Requires-Dist: flake8>=7.3.0; extra == "dev"
Requires-Dist: flake8-pyproject>=1.2.3; extra == "dev"
Requires-Dist: mypy>=1.18.2; extra == "dev"
Requires-Dist: types-PyYAML>=6.0.12.20250915; extra == "dev"
Requires-Dist: types-requests>=2.32.4.20250913; extra == "dev"
Requires-Dist: types-setuptools>=80.9.0.20250822; extra == "dev"
Requires-Dist: flake8-bugbear>=25.10.21; extra == "dev"
Requires-Dist: flake8-comprehensions>=3.17.0; extra == "dev"
Requires-Dist: flake8-annotations>=3.2.0; extra == "dev"
Requires-Dist: flake8-docstrings>=1.7.0; extra == "dev"
Requires-Dist: build; extra == "dev"
Requires-Dist: twine; extra == "dev"
Provides-Extra: gcp
Requires-Dist: langchain-google-vertexai>=0.1.0; extra == "gcp"
Requires-Dist: google-auth>=2.30.0; extra == "gcp"
Provides-Extra: aws
Requires-Dist: langchain-aws>=0.1.0; extra == "aws"
Requires-Dist: boto3>=1.34.0; extra == "aws"
Requires-Dist: botocore>=1.34.0; extra == "aws"
Requires-Dist: opensearch-py>=2.6.0; extra == "aws"
Provides-Extra: azure
Requires-Dist: langchain-openai>=0.1.0; extra == "azure"
Requires-Dist: azure-identity>=1.17.0; extra == "azure"
Requires-Dist: azure-search-documents>=11.5.1; extra == "azure"
Provides-Extra: providers
Requires-Dist: rag-bencher[aws,azure,gcp]; extra == "providers"
Dynamic: license-file
